bayessizer/__init__.py
bayessizer/calculator.py
bayessizer/inference.py
bayessizer/mde.py
bayessizer/priors.py
bayes_sizer-1.0.3.dist-info/METADATA
bayes_sizer-1.0.3.dist-info/WHEEL
bayes_sizer-1.0.3.dist-info/top_level.txt
bayes_sizer-1.0.3.dist-info/RECORD
