Metadata-Version: 2.2
Name: bayes-sizer
Version: 1.0.3
Summary: A Bayesian sample size calculator
Project-URL: Homepage, https://github.com/allanbutler/bayes-sizer
Project-URL: Issues, https://github.com/allanbutler/bayes-sizer/issues
Requires-Python: >=3.12.0
Requires-Dist: numpy
Requires-Dist: scipy
Requires-Dist: pytest
Requires-Dist: ipykernel>=6.29.5
Requires-Dist: matplotlib>=3.7.5
Requires-Dist: seaborn>=0.13.2
